special_model/DictionaryModelConsts.py
special_model/SpecialModelFactory.py
special_model/__init__.py
SpecialModel-0.0.22.dist-info/LICENSE
SpecialModel-0.0.22.dist-info/METADATA
SpecialModel-0.0.22.dist-info/WHEEL
SpecialModel-0.0.22.dist-info/top_level.txt
SpecialModel-0.0.22.dist-info/RECORD
