Metadata-Version: 2.1
Name: SpecialModel
Version: 0.0.22
Summary: Dictionary Model
Home-page: https://github.com/DanielBNY/SpecialModel
Author: Daniel Ben Yaacov
Author-email: daniel.benyaacov@gmail.com
License: UNKNOWN
Project-URL: Bug Tracker, https://github.com/DanielBNY/SpecialModel/issues
Platform: UNKNOWN
Classifier: Programming Language :: Python :: 3
Classifier: License :: OSI Approved :: MIT License
Classifier: Operating System :: OS Independent
Requires-Python: >=3.6
License-File: LICENSE
